{
  "novel_name": "林轩传",
  "phase": "writing",
  "current_chapter": 17,
  "total_chapters": 10,
  "completed_chapters": [
    1,
    2,
    3,
    4,
    5,
    6,
    7,
    8,
    9,
    10,
    11,
    12,
    13,
    14,
    15,
    16
  ],
  "total_word_count": 124129,
  "chapter_word_counts": {
    "1": 5388,
    "10": 10104,
    "11": 8892,
    "12": 5489,
    "13": 11411,
    "14": 10742,
    "15": 6889,
    "16": 10599,
    "2": 6906,
    "3": 5630,
    "4": 6830,
    "5": 7673,
    "6": 5890,
    "7": 4596,
    "8": 8225,
    "9": 8865
  },
  "in_progress_chapter": 17,
  "flow": "writing",
  "strand_history": [
    "quest",
    "quest",
    "quest",
    "quest",
    "quest",
    "quest",
    "quest",
    "quest",
    "quest",
    "quest",
    "quest",
    "quest",
    "quest",
    "quest",
    "quest",
    "quest"
  ],
  "hook_history": [
    "desire",
    "crisis",
    "mystery",
    "mystery",
    "crisis",
    "crisis",
    "mystery",
    "mystery",
    "crisis",
    "crisis",
    "crisis",
    "crisis",
    "crisis",
    "crisis",
    "crisis",
    "desire"
  ],
  "current_volume": 1,
  "current_arc": 1,
  "layered": true
}